Metadata-Version: 1.1
Name: effluxpy
Version: 0.5.8
Summary: Advanced Browser and Streamer Python
Home-page: https://github.com/jkabhishek/effluxpy
Author: Abhishek Kumar Jaiswal
Author-email: abhishekjaiswal.kol@gmail.com
License: MIT
Download-URL: https://github.com/jkabhishek/effluxpy/archive/0.5.8.tar.gz
Keywords: web,file,browser
Platform: any
Classifier: Development Status :: 4 - Beta
Classifier: License :: OSI Approved :: MIT License
Classifier: Operating System :: OS Independent
Classifier: Programming Language :: Python
Classifier: Programming Language :: Python :: 3
